roboverse/__init__.py
roboverse-0.0.0.dev0.dist-info/entry_points.txt
roboverse-0.0.0.dev0.dist-info/LICENSE
roboverse-0.0.0.dev0.dist-info/WHEEL
roboverse-0.0.0.dev0.dist-info/METADATA
roboverse-0.0.0.dev0.dist-info/RECORD
