Metadata-Version: 2.1
Name: roboverse
Version: 0.0.0.dev0
Summary: Robotics Metaverse
Home-page: https://GitHub.com/Mindstem/Roboverse
License: MIT
Keywords: Robotics,robot,robots,Artificial Intelligence,A.I.,AI,metaverse
Author: The Vinh LUONG (LƯƠNG Thế Vinh)
Author-email: Vinh@STEAMforVietNam.org
Maintainer: The Vinh LUONG (LƯƠNG Thế Vinh)
Maintainer-email: Vinh@STEAMforVietNam.org
Requires-Python: >=3.10,<4
Classifier: Development Status :: 3 - Alpha
Classifier: Environment :: MacOS X
Classifier: Environment :: Win32 (MS Windows)
Classifier: Intended Audience :: Developers
Classifier: Intended Audience :: Education
Classifier: Intended Audience :: Information Technology
Classifier: Intended Audience :: Manufacturing
Classifier: Intended Audience :: Science/Research
Classifier: License :: OSI Approved :: MIT License
Classifier: Operating System :: MacOS
Classifier: Operating System :: MacOS :: MacOS X
Classifier: Operating System :: Microsoft
Classifier: Operating System :: Microsoft :: Windows
Classifier: Operating System :: Microsoft :: Windows :: Windows 10
Classifier: Operating System :: Microsoft :: Windows :: Windows 7
Classifier: Operating System :: Microsoft :: Windows :: Windows 8
Classifier: Operating System :: Microsoft :: Windows :: Windows 8.1
Classifier: Operating System :: OS Independent
Classifier: Operating System :: Other OS
Classifier: Operating System :: POSIX
Classifier: Operating System :: POSIX :: Linux
Classifier: Programming Language :: Python
Classifier: Programming Language :: Python :: 3
Classifier: Programming Language :: Python :: 3.10
Classifier: Programming Language :: Python :: 3.11
Classifier: Topic :: Education
Classifier: Topic :: Home Automation
Classifier: Topic :: Scientific/Engineering
Classifier: Topic :: Scientific/Engineering :: Artificial Intelligence
Classifier: Topic :: Scientific/Engineering :: Human Machine Interfaces
Classifier: Topic :: Scientific/Engineering :: Mathematics
Classifier: Topic :: Scientific/Engineering :: Physics
Classifier: Topic :: Scientific/Engineering :: Visualization
Classifier: Topic :: Software Development
Classifier: Topic :: Software Development :: Libraries
Classifier: Topic :: Software Development :: Libraries :: Application Frameworks
Classifier: Topic :: Software Development :: Libraries :: Python Modules
Classifier: Topic :: Software Development :: User Interfaces
Classifier: Topic :: Software Development :: Widget Sets
Provides-Extra: doc
Provides-Extra: lint
Provides-Extra: test
Project-URL: Documentation, https://Mindstem.GitHub.io/Roboverse
Project-URL: GitHub, https://GitHub.com/Mindstem/Roboverse
Project-URL: Repository, https://GitHub.com/Mindstem/Roboverse
